llm_agents_from_scratch/__init__.py
llm_agents_from_scratch/_version.py
llm_agents_from_scratch/logger.py
llm_agents_from_scratch/py.typed
llm_agents_from_scratch/utils.py
llm_agents_from_scratch/agent/__init__.py
llm_agents_from_scratch/agent/builder.py
llm_agents_from_scratch/agent/llm_agent.py
llm_agents_from_scratch/agent/templates/__init__.py
llm_agents_from_scratch/agent/templates/defaults.py
llm_agents_from_scratch/agent/templates/llm_agent.py
llm_agents_from_scratch/base/__init__.py
llm_agents_from_scratch/base/llm.py
llm_agents_from_scratch/base/tool.py
llm_agents_from_scratch/data_structures/__init__.py
llm_agents_from_scratch/data_structures/agent.py
llm_agents_from_scratch/data_structures/llm.py
llm_agents_from_scratch/data_structures/tool.py
llm_agents_from_scratch/errors/__init__.py
llm_agents_from_scratch/errors/agent.py
llm_agents_from_scratch/errors/core.py
llm_agents_from_scratch/errors/mcp.py
llm_agents_from_scratch/errors/task_handler.py
llm_agents_from_scratch/listings/__init__.py
llm_agents_from_scratch/listings/ch02/__init__.py
llm_agents_from_scratch/llms/__init__.py
llm_agents_from_scratch/llms/ollama/__init__.py
llm_agents_from_scratch/llms/ollama/llm.py
llm_agents_from_scratch/llms/ollama/utils.py
llm_agents_from_scratch/llms/openai/__init__.py
llm_agents_from_scratch/llms/openai/errors.py
llm_agents_from_scratch/llms/openai/llm.py
llm_agents_from_scratch/llms/openai/utils.py
llm_agents_from_scratch/notebook_utils/__init__.py
llm_agents_from_scratch/notebook_utils/pandas.py
llm_agents_from_scratch/tools/__init__.py
llm_agents_from_scratch/tools/pydantic_function.py
llm_agents_from_scratch/tools/simple_function.py
llm_agents_from_scratch/tools/mcp/__init__.py
llm_agents_from_scratch/tools/mcp/provider.py
llm_agents_from_scratch/tools/mcp/tool.py
llm_agents_from_scratch-0.0.13.dist-info/METADATA
llm_agents_from_scratch-0.0.13.dist-info/WHEEL
llm_agents_from_scratch-0.0.13.dist-info/licenses/LICENSE
llm_agents_from_scratch-0.0.13.dist-info/RECORD
