Metadata-Version: 2.4
Name: llm-agents-from-scratch
Version: 0.0.13
Summary: Build an LLM agent, equipped with MCP, from scratch.
Author-email: Andrei Fajardo <andrei@nerdai.io>
License-Expression: Apache-2.0
License-File: LICENSE
Requires-Python: >=3.10
Requires-Dist: asyncio>=3.4.3
Requires-Dist: colorama>=0.4.6
Requires-Dist: jsonschema>=4.24.0
Requires-Dist: mcp[cli]>=1.9.4
Requires-Dist: ollama>=0.5.1
Requires-Dist: pydantic>=2.11.7
Requires-Dist: typing-extensions>=4.14.0
Provides-Extra: notebook-utils
Requires-Dist: pandas>=2.3.3; extra == 'notebook-utils'
Provides-Extra: notebooks
Requires-Dist: ipython>=8.37.0; extra == 'notebooks'
Provides-Extra: openai
Requires-Dist: openai>=2.9.0; extra == 'openai'
